<annotation>
  <folder>input</folder>
  <filename>55.webp</filename>
  <path>C:\Users\Praveen Kumar\Desktop\Yolo-Training-GoogleColab-master\Yolo-Training-GoogleColab-master\data_converstion\main\input\55.webp</path>
  <source>
    <database>Unknown</database>
  </source>
  <size>
    <width>400</width>
    <height>300</height>
    <depth>3</depth>
  </size>
  <segmented>0</segmented>
  <object>
    <name>bike</name>
    <pose>Unspecified</pose>
    <truncated>0</truncated>
    <difficult>0</difficult>
    <bndbox>
      <xmin>84</xmin>
      <ymin>99</ymin>
      <xmax>318</xmax>
      <ymax>295</ymax>
    </bndbox>
  </object>
</annotation>
