<annotation>
  <folder>input</folder>
  <filename>59.jpg</filename>
  <path>C:\Users\Praveen Kumar\Desktop\Yolo-Training-GoogleColab-master\Yolo-Training-GoogleColab-master\data_converstion\main\input\59.jpg</path>
  <source>
    <database>Unknown</database>
  </source>
  <size>
    <width>450</width>
    <height>317</height>
    <depth>3</depth>
  </size>
  <segmented>0</segmented>
  <object>
    <name>bike</name>
    <pose>Unspecified</pose>
    <truncated>0</truncated>
    <difficult>0</difficult>
    <bndbox>
      <xmin>70</xmin>
      <ymin>116</ymin>
      <xmax>169</xmax>
      <ymax>254</ymax>
    </bndbox>
  </object>
  <object>
    <name>bike</name>
    <pose>Unspecified</pose>
    <truncated>0</truncated>
    <difficult>0</difficult>
    <bndbox>
      <xmin>277</xmin>
      <ymin>137</ymin>
      <xmax>377</xmax>
      <ymax>275</ymax>
    </bndbox>
  </object>
</annotation>
